deltastore/__init__.py
deltastore/profile.py
deltastore/protocols.py
deltastore/reader.py
deltastore/restclient.py
deltastore/version.py
deltastore-0.9.2.dist-info/METADATA
deltastore-0.9.2.dist-info/WHEEL
deltastore-0.9.2.dist-info/top_level.txt
deltastore-0.9.2.dist-info/RECORD
