Metadata-Version: 2.1
Name: deltastore
Version: 0.9.2
Summary: Python Connector for DeltaStore
Home-page: https://github.com/dataplatform-lab/deltastore
Author: The Delta Store Project Authors
Author-email: haruband@gmail.com
Requires-Python: >= 3.8
Requires-Dist: pandas
Requires-Dist: pyarrow
Requires-Dist: pytest
